{
	"@type":"Subset",
	"Name":"PLDist_FY24-CA_CoOwned",
	"Alias":"Name",
	"Elements":
	[
		{
			"@id":"Dimensions('D365_Locations')/Hierarchies('D365_Locations')/Elements('CA COOWNED DISTRICT TOTAL')"
		},
		{
			"@id":"Dimensions('D365_Locations')/Hierarchies('D365_Locations')/Elements('DISTRICT 15 (CA Central) - Tucker')"
		},
		{
			"@id":"Dimensions('D365_Locations')/Hierarchies('D365_Locations')/Elements('CA - Sacramento')"
		},
		{
			"@id":"Dimensions('D365_Locations')/Hierarchies('D365_Locations')/Elements('CA - Fresno')"
		},
		{
			"@id":"Dimensions('D365_Locations')/Hierarchies('D365_Locations')/Elements('CA - San Jose')"
		},
		{
			"@id":"Dimensions('D365_Locations')/Hierarchies('D365_Locations')/Elements('CA - Oakland')"
		},
		{
			"@id":"Dimensions('D365_Locations')/Hierarchies('D365_Locations')/Elements('CA - Fair Oaks')"
		},
		{
			"@id":"Dimensions('D365_Locations')/Hierarchies('D365_Locations')/Elements('CA - Concord')"
		},
		{
			"@id":"Dimensions('D365_Locations')/Hierarchies('D365_Locations')/Elements('CA - Stockton')"
		},
		{
			"@id":"Dimensions('D365_Locations')/Hierarchies('D365_Locations')/Elements('CA - Pleasanton')"
		},
		{
			"@id":"Dimensions('D365_Locations')/Hierarchies('D365_Locations')/Elements('CA - Colma')"
		},
		{
			"@id":"Dimensions('D365_Locations')/Hierarchies('D365_Locations')/Elements('CA - Northridge')"
		},
		{
			"@id":"Dimensions('D365_Locations')/Hierarchies('D365_Locations')/Elements('CA - Pasadena')"
		},
		{
			"@id":"Dimensions('D365_Locations')/Hierarchies('D365_Locations')/Elements('CA - West Covina')"
		},
		{
			"@id":"Dimensions('D365_Locations')/Hierarchies('D365_Locations')/Elements('CA - Upland')"
		},
		{
			"@id":"Dimensions('D365_Locations')/Hierarchies('D365_Locations')/Elements('CA - Ventura')"
		},
		{
			"@id":"Dimensions('D365_Locations')/Hierarchies('D365_Locations')/Elements('CA - Rancho Mirage')"
		},
		{
			"@id":"Dimensions('D365_Locations')/Hierarchies('D365_Locations')/Elements('CA - San Diego')"
		},
		{
			"@id":"Dimensions('D365_Locations')/Hierarchies('D365_Locations')/Elements('CA - La Mesa')"
		},
		{
			"@id":"Dimensions('D365_Locations')/Hierarchies('D365_Locations')/Elements('CA - Escondido')"
		},
		{
			"@id":"Dimensions('D365_Locations')/Hierarchies('D365_Locations')/Elements('CA - Encinitas')"
		},
		{
			"@id":"Dimensions('D365_Locations')/Hierarchies('D365_Locations')/Elements('CA - Chula Vista')"
		},
		{
			"@id":"Dimensions('D365_Locations')/Hierarchies('D365_Locations')/Elements('CA - Anaheim')"
		},
		{
			"@id":"Dimensions('D365_Locations')/Hierarchies('D365_Locations')/Elements('CA - Lake Forest')"
		},
		{
			"@id":"Dimensions('D365_Locations')/Hierarchies('D365_Locations')/Elements('CA - Huntington Beach')"
		}
	]
}